{
  "ComponentIndexes": {},
  "ControlUniqueGuids": {},
  "ControlUniqueIds": {
    "AffichageConditionnel": 3,
    "App": 1,
    "DatePicker1": 14,
    "Gallery2": 9,
    "Gallery6": 33,
    "Gallery8template1": 19,
    "galleryTemplate2_29": 11,
    "galleryTemplate2_30": 20,
    "galleryTemplate2_31": 31,
    "galleryTemplate3": 16,
    "galleryTemplate6": 34,
    "inputDate": 10,
    "inputString": 17,
    "inputString_1": 30,
    "Label1": 22,
    "Label1_1": 35,
    "Label4": 6,
    "Label5": 4,
    "Label6": 26,
    "Label6_1": 27,
    "Label7": 28,
    "lblBot": 15,
    "lblBot_1": 25,
    "lblBot_2": 38,
    "lblMid": 13,
    "lblMid_1": 23,
    "lblMid_2": 36,
    "lblTop": 12,
    "lblTop_1": 21,
    "lblTop_2": 32,
    "listRemove": 42,
    "listString": 41,
    "multipleAdd": 39,
    "multipleClear": 43,
    "multipleList": 18,
    "Screen1": 8,
    "Screen3": 29,
    "TextInput1": 24,
    "TextInput1_1": 37,
    "TextInput2_1": 5,
    "TextInput3": 7
  },
  "FunctionParamsInvariantScripts": {},
  "FunctionParamsInvariantScriptsOnInstances": {},
  "HeaderLastSavedDateTimeUTC": "02/11/2023 16:58:12",
  "IsLegacyComponentAllowGlobalScopeCase": false,
  "LocalConnectionIDReferences": {
    "5a6fa880-d4f3-4613-a69e-d0c980a0eb7c": "\"/providers/microsoft.powerapps/apis/shared_sharepointonline/connections/c647b609193c4fe7baadc24b6119276b\""
  },
  "LocalDatabaseReferencesAsEmpty": false,
  "LocalResourceFileNames": {},
  "LocalResourceRootPaths": {},
  "OrderComponentMetadata": {},
  "OrderComponentTemplate": {},
  "OrderDataSource": {
    "cQuestions": 4,
    "CustomGallerySample": 0,
    "DropDownSample": 1,
    "Forms": 2,
    "Questions": 3
  },
  "OrderGroupControls": {},
  "OrderPcfTemplate": {},
  "OrderTemplate": {},
  "OrderXMLTemplate": {
    "datepicker": 4,
    "gallery": 2,
    "htmlViewer": 3,
    "icon": 5,
    "label": 0,
    "text": 1
  },
  "OverridablePropertiesEntry": {
    "AffichageConditionnel": {},
    "App": {},
    "DatePicker1": {},
    "Gallery2": {},
    "Gallery6": {},
    "Gallery8template1": {},
    "galleryTemplate2_29": {},
    "galleryTemplate2_30": {},
    "galleryTemplate2_31": {},
    "galleryTemplate3": {},
    "galleryTemplate6": {},
    "inputDate": {},
    "inputString": {},
    "inputString_1": {},
    "Label1": {},
    "Label1_1": {},
    "Label4": {},
    "Label5": {},
    "Label6": {},
    "Label6_1": {},
    "Label7": {},
    "lblBot": {},
    "lblBot_1": {},
    "lblBot_2": {},
    "lblMid": {},
    "lblMid_1": {},
    "lblMid_2": {},
    "lblTop": {},
    "lblTop_1": {},
    "lblTop_2": {},
    "listRemove": {},
    "listString": {},
    "multipleAdd": {},
    "multipleClear": {},
    "multipleList": {},
    "Screen1": {},
    "Screen3": {},
    "TextInput1": {},
    "TextInput1_1": {},
    "TextInput2_1": {},
    "TextInput3": {}
  },
  "PCFDynamicSchemaForIRRetrievalEntry": {},
  "PublishOrderIndices": {
    "AffichageConditionnel": 1,
    "App": 0,
    "DatePicker1": 18,
    "Gallery2": 8,
    "Gallery6": 32,
    "Gallery8template1": 27,
    "galleryTemplate2_29": 15,
    "galleryTemplate2_30": 21,
    "galleryTemplate2_31": 30,
    "galleryTemplate3": 11,
    "galleryTemplate6": 37,
    "inputDate": 10,
    "inputString": 12,
    "inputString_1": 29,
    "Label1": 23,
    "Label1_1": 33,
    "Label4": 4,
    "Label5": 2,
    "Label6": 13,
    "Label6_1": 14,
    "Label7": 9,
    "lblBot": 19,
    "lblBot_1": 26,
    "lblBot_2": 36,
    "lblMid": 17,
    "lblMid_1": 24,
    "lblMid_2": 34,
    "lblTop": 16,
    "lblTop_1": 22,
    "lblTop_2": 31,
    "listRemove": 0,
    "listString": 0,
    "multipleAdd": 0,
    "multipleClear": 0,
    "multipleList": 20,
    "Screen1": 7,
    "Screen3": 28,
    "TextInput1": 25,
    "TextInput1_1": 35,
    "TextInput2_1": 3,
    "TextInput3": 5
  },
  "ResourcesJsonIndices": {
    "Image-SampleImage": 0
  },
  "RuleScreenIdWithoutScreen": {},
  "TemplateVersions": {},
  "VolatileProperties": {
    "AnalysisLoadTime": 0.1204336,
    "ControlCount": {
      "datepicker": 1,
      "gallery": 6,
      "galleryTemplate": 6,
      "htmlViewer": 9,
      "label": 7,
      "screen": 3,
      "text": 4
    },
    "DeserializationLoadTime": 0.2121221,
    "ErrorCount": 10
  },
  "WasLocalDatabaseReferencesEmpty": true
}